LICENSE
solvor/__init__.py
solvor/_solvor_rust.cpython-312-aarch64-linux-gnu.so
solvor/a_star.py
solvor/anneal.py
solvor/articulation.py
solvor/bayesian.py
solvor/bellman_ford.py
solvor/bfgs.py
solvor/bfs.py
solvor/bin_pack.py
solvor/bp.py
solvor/cg.py
solvor/community.py
solvor/cp.py
solvor/cp_encoder.py
solvor/differential_evolution.py
solvor/dijkstra.py
solvor/dlx.py
solvor/flow.py
solvor/floyd_warshall.py
solvor/genetic.py
solvor/gradient.py
solvor/hungarian.py
solvor/interior_point.py
solvor/job_shop.py
solvor/kcore.py
solvor/knapsack.py
solvor/lns.py
solvor/milp.py
solvor/mst.py
solvor/nelder_mead.py
solvor/network_simplex.py
solvor/pagerank.py
solvor/particle_swarm.py
solvor/powell.py
solvor/py.typed
solvor/rust/__init__.py
solvor/rust/adapters.py
solvor/sat.py
solvor/scc.py
solvor/simplex.py
solvor/tabu.py
solvor/types.py
solvor/utils/__init__.py
solvor/utils/data_structures.py
solvor/utils/helpers.py
solvor/utils/pricing.py
solvor/utils/validate.py
solvor/vrp.py
solvor-0.6.1.dist-info/METADATA
solvor-0.6.1.dist-info/WHEEL
solvor-0.6.1.dist-info/licenses/LICENSE
solvor-0.6.1.dist-info/RECORD
