Metadata-Version: 2.4
Name: solvor
Version: 0.6.1
Classifier: Development Status :: 4 - Beta
Classifier: Intended Audience :: Developers
Classifier: License :: OSI Approved :: Apache Software License
Classifier: Programming Language :: Python :: 3.12
Classifier: Programming Language :: Python :: 3.13
Classifier: Programming Language :: Python :: 3.14
Classifier: Topic :: Scientific/Engineering :: Mathematics
Requires-Dist: pytest>=9.0.2 ; extra == 'dev'
Requires-Dist: pytest-cov>=7.0.0 ; extra == 'dev'
Requires-Dist: ruff>=0.14.14 ; extra == 'dev'
Requires-Dist: pre-commit>=4.5.1 ; extra == 'dev'
Requires-Dist: ty>=0.0.14 ; extra == 'dev'
Requires-Dist: maturin>=1.7,<2.0 ; extra == 'dev'
Requires-Dist: prek>=0.3.1 ; extra == 'dev'
Requires-Dist: mkdocs>=1.6 ; extra == 'docs'
Requires-Dist: mkdocs-material>=9.5 ; extra == 'docs'
Requires-Dist: mkdocstrings[python]>=1.0.2 ; extra == 'docs'
Requires-Dist: mkdocs-git-revision-date-localized-plugin>=1.5.1 ; extra == 'docs'
Provides-Extra: dev
Provides-Extra: docs
License-File: LICENSE
Summary: Solvor all your optimization needs.
Keywords: optimization,solver,linear-programming,sat,metaheuristics,operations-research
Author: Steven Grond
License: Apache-2.0
Requires-Python: >=3.12
Project-URL: PyPI, https://pypi.org/project/solvOR/
Project-URL: Repository, https://github.com/StevenBtw/solvOR
Project-URL: Website, https://solvOR.ai
